Workbook

Sheet Panier
A1: Panier PC gaming ASUS, Core Ultra 7 + RTX 5060
A2: Prix relevés sur ldlc.com le 1er octobre 2026, boîtier non inclus (acheté sur place en Polynésie).
A4: Pièce | B4: Produit | C4: Fiche LDLC | D4: Prix TTC France (€) | E4: Prix HT DOM-TOM (€) | F4: Ajouté au panier ? | G4: Remarque
A5: Processeur | B5: Intel Core Ultra 7 270K Plus | C5: Voir la fiche | D5: 399.95 | E5: =D5/(1+'Coût final'!$C$5) -> 333.29167 | F5: Non | G5: 24 cœurs, puce graphique intégrée
A6: Ventirad | B6: Thermalright Peerless Assassin 120 SE | C6: Voir la fiche | D6: 45 | E6: =D6/(1+'Coût final'!$C$5) -> 37.5 | F6: Non | G6: Prix estimé : à vérifier sur la fiche
A7: Carte mère | B7: ASUS TUF GAMING B860-PLUS WIFI | C7: Voir la fiche | D7: 259.95 | E7: =D7/(1+'Coût final'!$C$5) -> 216.625 | F7: Non | G7: Gamme TUF, Wi-Fi 7, 4 emplacements RAM
A8: Mémoire | B8: Kingston FURY Beast 16 Go (2 × 8 Go) DDR5 6000 CL30 | C8: Voir la fiche | D8: 381.95 | E8: =D8/(1+'Coût final'!$C$5) -> 318.29167 | F8: Non | G8: 16 Go maintenant, extensible plus tard
A9: Carte graphique | B9: ASUS TUF Gaming GeForce RTX 5060 OC 8 Go | C9: Voir la fiche | D9: 559.95 | E9: =D9/(1+'Coût final'!$C$5) -> 466.625 | F9: Non | G9: À remplacer plus tard par une carte plus puissante
A10: SSD | B10: Samsung SSD 990 NVMe 1 To | C10: Voir la fiche | D10: 199.95 | E10: =D10/(1+'Coût final'!$C$5) -> 166.625 | F10: Non
A11: Alimentation | B11: Corsair RM850e (2025) | C11: Voir la fiche | D11: 134.95 | E11: =D11/(1+'Coût final'!$C$5) -> 112.45833 | F11: Non | G11: 850 W, garantie constructeur 7 ans
A12: Total pièces | D12: =SUM(D5:D11) -> 1981.7 | E12: =SUM(E5:E11) -> 1651.4167 | F12: =COUNTIF(F5:F11,"Oui")&" / 7 ajoutées" -> 0 / 7 ajoutées
A14: Mode d'emploi
A15: Texte bleu = valeur que tu peux modifier (prix si LDLC a changé, Oui/Non quand la pièce est dans ton panier). Tout le reste se calcule seul.
A16: Le coût final douane comprise est dans l'onglet « Coût final ». Les variantes moins chères sont dans l'onglet « Options ».

Sheet Coût final
A1: Coût réel arrivé en Polynésie
A2: Modifie les cellules surlignées en jaune ou en bleu : le total se recalcule.
B4: Paramètre | C4: Valeur | D4: Source ou commentaire
B5: TVA française retirée par LDLC | C5: 0.2 | D5: LDLC facture les commandes DOM-TOM hors taxe (ldlc.com/aide/22-livraison-dans-les-dom-tom)
B6: Frais de port LDLC | C6: 150 | D6: Hypothèse : remplace par le montant affiché par LDLC à l'étape paiement
B7: Droit de douane | C7: 0.1 | D7: Taux des ordinateurs portables (position 8471 30 00), hypothèse prudente pour les composants
B8: TEAP | C8: 0.02 | D8: Taxe pour l'environnement, l'agriculture et la pêche
B9: Péage | C9: 0.0125 | D9: Douane de Polynésie française
B10: TEEI | C10: 0.01 | D10: Taxe sur les équipements électriques importés
B11: Petites taxes fixes (PID, SETIL, statistique) | C11: 6 | D11: Estimation : PID 85 XPF par article de déclaration + SETIL + taxe statistique
B12: TVA Polynésie | C12: 0.16 | D12: Taux normal, appliqué sur la valeur CAF + droits et taxes
B13: Frais de dédouanement | C13: 60 | D13: Estimation : au-delà de 50 000 XPF, déclaration par un commissionnaire en douane à tes frais
B14: Budget maximum | C14: 2500 | D14: Ton budget
B15: Taux de change (XPF pour 1 €) | C15: 119.332 | D15: Parité fixe euro / franc Pacifique
B18: Calcul | C18: Montant
B19: Pièces hors taxe (onglet Panier) | C19: =Panier!E12 -> 1651.4167
B20: Valeur CAF (pièces HT + port) | C20: =C19+C6 -> 1801.4167
B21: Droit de douane | C21: =C20*C7 -> 180.14167
B22: TEAP + péage + TEEI | C22: =C20*(C8+C9+C10) -> 76.560208
B23: Petites taxes fixes | C23: =C11 -> 6
B24: Base de calcul de la TVA polynésienne | C24: =C20+C21+C22+C23 -> 2064.1185
B25: TVA Polynésie | C25: =C24*C12 -> 330.25897
B26: Total à payer à la douane | C26: =C21+C22+C23+C25 -> 592.96084
B27: Total à payer à la douane, en XPF | C27: =ROUND(C26*C15,0) -> 70759
B28: Frais de dédouanement | C28: =C13 -> 60
B29: COÛT TOTAL ARRIVÉ CHEZ TOI | C29: =C20+C26+C28 -> 2454.3775
B30: Coût total en francs Pacifique | C30: =ROUND(C29*C15,0) -> 292886
B31: Écart avec le budget (positif = marge restante) | C31: =C14-C29 -> 45.622492
B32: Verdict | C32: =IF(C31>=0,"Dans le budget, marge de "&ROUND(C31,0)&" €","Hors budget de "&ROUND(-C31,0)&" €") -> Dans le budget, marge de 46 €
B33: Frais de port maximum pour rester dans le budget | C33: =MAX(0,C6+C31/((1+C7+C8+C9+C10)*(1+C12))) -> 184.42428
B35: Estimation : le montant exact sera celui de la déclaration en douane. Taux issus du tarif des douanes de Polynésie française.

Sheet Options
A1: Variantes possibles
A2: Chaque ligne montre le coût total si tu fais seulement ce changement-là.
A4: Option | B4: Remplace | C4: Fiche LDLC | D4: Prix option TTC (€) | E4: Prix actuel TTC (€) | F4: Écart TTC (€) | G4: Coût total arrivé (€) | H4: En XPF | I4: Budget
A5: ASUS PRIME B860-PLUS WIFI | B5: Carte mère TUF | C5: Voir la fiche | D5: 229.95 | E5: =Panier!D7 -> 259.95 | F5: =D5-E5 -> -30 | G5: ='Coût final'!$C$29+F5*(1+'Coût final'!$C$7+'Coût final'!$C$8+'Coût final'!$C$9+'Coût final'!$C$10)*(1+'Coût final'!$C$12)/(1+'Coût final'!$C$5) -> 2421.245 | H5: =ROUND(G5*'Coût final'!$C$15,0) -> 288932 | I5: =IF(G5<='Coût final'!$C$14,"OK","Dépasse") -> OK
A6: Cooler Master Elite Gold 850 | B6: Alimentation Corsair | C6: Voir la fiche | D6: 99.95 | E6: =Panier!D11 -> 134.95 | F6: =D6-E6 -> -35 | G6: ='Coût final'!$C$29+F6*(1+'Coût final'!$C$7+'Coût final'!$C$8+'Coût final'!$C$9+'Coût final'!$C$10)*(1+'Coût final'!$C$12)/(1+'Coût final'!$C$5) -> 2415.7229 | H6: =ROUND(G6*'Coût final'!$C$15,0) -> 288273 | I6: =IF(G6<='Coût final'!$C$14,"OK","Dépasse") -> OK
A7: ASUS Dual GeForce RTX 5060 OC 8 Go | B7: Carte graphique TUF | C7: Voir la fiche | D7: 549.95 | E7: =Panier!D9 -> 559.95 | F7: =D7-E7 -> -10 | G7: ='Coût final'!$C$29+F7*(1+'Coût final'!$C$7+'Coût final'!$C$8+'Coût final'!$C$9+'Coût final'!$C$10)*(1+'Coût final'!$C$12)/(1+'Coût final'!$C$5) -> 2443.3333 | H7: =ROUND(G7*'Coût final'!$C$15,0) -> 291568 | I7: =IF(G7<='Coût final'!$C$14,"OK","Dépasse") -> OK
A8: Textorm 32 Go (2 × 16 Go) DDR5 6000 CL36 | B8: Mémoire 16 Go | C8: Voir la fiche | D8: 609.95 | E8: =Panier!D8 -> 381.95 | F8: =D8-E8 -> 228 | G8: ='Coût final'!$C$29+F8*(1+'Coût final'!$C$7+'Coût final'!$C$8+'Coût final'!$C$9+'Coût final'!$C$10)*(1+'Coût final'!$C$12)/(1+'Coût final'!$C$5) -> 2706.1845 | H8: =ROUND(G8*'Coût final'!$C$15,0) -> 322934 | I8: =IF(G8<='Coût final'!$C$14,"OK","Dépasse") -> Dépasse
A10: Texte vert = valeur reprise de l'onglet Panier. Pour adopter une option, remplace le produit et son prix dans l'onglet Panier.

Sheet À savoir
A1: À savoir avant et après la commande
A2: Jeux visés : Battlefield 6, Dune: Awakening, ARC Raiders, Once Human.
A4: Jeu | B4: Carte graphique recommandée | C4: Processeur recommandé
A5: Battlefield 6 | B5: RTX 3060 Ti / RX 6700 XT | C5: Core i7-10700 / Ryzen 7 3700X
A6: Dune: Awakening | B6: RTX 3070 / RX 6700 XT | C6: Core i7-10700K / Ryzen 5 2600X
A7: ARC Raiders | B7: RTX 2070 / RX 5700 XT | C7: Core i5-9600K / Ryzen 5 3600
A8: Once Human | B8: GTX 1060 / RX 580 | C8: Core i7-7700
A9: Avec la RTX 5060 (8 Go) : vise le 1080p en élevé, ou le 1440p avec le DLSS 4. La future carte graphique ouvrira le 1440p en élevé.
A11: Checklist
A12: ☐ Boîtier acheté sur place : format ATX, ventirad jusqu'à 160 mm de haut, carte graphique de la longueur du modèle choisi, filtres à poussière.
A13: ☐ Mettre le BIOS de la carte mère à jour avant d'installer Windows.
A14: ☐ Battlefield 6 : activer le TPM (Intel PTT) et le Secure Boot dans le BIOS.
A15: ☐ Prévoir une licence Windows : elle n'est pas dans le panier.
A16: ☐ Brancher le PC sur une multiprise parafoudre ou un onduleur (orages), dépoussiérer tous les 3 à 6 mois.
A17: ☐ L'alimentation 850 W est déjà dimensionnée pour la future carte graphique.
A18: ☐ LDLC peut imposer Chronopost au lieu de Colissimo pour un colis lourd : le port change alors.
A19: ☐ Garder les emballages et tester toutes les pièces dès réception : un retour SAV vers la métropole coûte cher.
A21: Sources
A22: LDLC, livraison dans les DOM-TOM
... A24: Douane, 10 questions sur l'export vers la Polynésie
